{
  "pageProps": {
    "dehydratedState": {
      "mutations": [],
      "queries": [
        {
          "state": {
            "data": {
              "meta": {
                "code": 0,
                "message": "SUCCESS"
              },
              "data": [
                {
                  "gnbSeq": 95,
                  "sortNum": 1,
                  "menuName": "레고",
                  "exposeStartDate": "2024-08-02 00:00:00",
                  "exposeEndDate": "2024-09-01 23:59:00",
                  "badgeType": 0,
                  "badgeExposeStartDate": "2025-04-15 10:32:09",
                  "badgeExposeEndDate": "9999-12-31 23:59:59"
                },
                {
                  "gnbSeq": 97,
                  "sortNum": 999,
                  "menuName": "미개봉상품",
                  "exposeStartDate": "2024-10-14 00:00:00",
                  "exposeEndDate": "2024-10-31 23:59:00",
                  "badgeType": 0,
                  "badgeExposeStartDate": "2025-04-15 10:32:09",
                  "badgeExposeEndDate": "9999-12-31 23:59:59"
                },
                {
                  "gnbSeq": 99,
                  "sortNum": 999,
                  "menuName": "미개봉상품",
                  "exposeStartDate": "2024-11-01 09:00:00",
                  "exposeEndDate": "2024-11-22 23:59:00",
                  "badgeType": 0,
                  "badgeExposeStartDate": "2025-04-15 10:32:09",
                  "badgeExposeEndDate": "9999-12-31 23:59:59"
                },
                {
                  "gnbSeq": 100,
                  "sortNum": 999,
                  "menuName": "미개봉 키덜트",
                  "exposeStartDate": "2024-12-16 00:00:00",
                  "exposeEndDate": "2025-01-12 23:59:00",
                  "badgeType": 0,
                  "badgeExposeStartDate": "2025-04-15 10:32:09",
                  "badgeExposeEndDate": "9999-12-31 23:59:59"
                },
                {
                  "gnbSeq": 101,
                  "sortNum": 999,
                  "menuName": "콘서트/공연티켓",
                  "exposeStartDate": "2024-12-24 00:00:00",
                  "exposeEndDate": "2025-01-14 23:59:00",
                  "badgeType": 0,
                  "badgeExposeStartDate": "2025-04-15 10:32:09",
                  "badgeExposeEndDate": "9999-12-31 23:59:59"
                },
                {
                  "gnbSeq": 102,
                  "sortNum": 999,
                  "menuName": "닌텐도 ",
                  "exposeStartDate": "2025-01-20 00:00:00",
                  "exposeEndDate": "2025-02-17 23:59:00",
                  "badgeType": 0,
                  "badgeExposeStartDate": "2025-04-15 10:32:00",
                  "badgeExposeEndDate": "9999-12-31 23:59:00"
                },
                {
                  "gnbSeq": 103,
                  "sortNum": 999,
                  "menuName": "신학기 노트북",
                  "exposeStartDate": "2025-02-25 00:00:00",
                  "exposeEndDate": "2025-03-11 23:59:00",
                  "badgeType": 0,
                  "badgeExposeStartDate": "2025-04-15 10:32:09",
                  "badgeExposeEndDate": "9999-12-31 23:59:59"
                },
                {
                  "gnbSeq": 105,
                  "sortNum": 999,
                  "menuName": "그래픽카드",
                  "exposeStartDate": "2025-03-12 00:00:00",
                  "exposeEndDate": "2025-04-02 23:59:00",
                  "badgeType": 0,
                  "badgeExposeStartDate": "2025-04-15 10:32:09",
                  "badgeExposeEndDate": "9999-12-31 23:59:59"
                },
                {
                  "gnbSeq": 107,
                  "sortNum": 999,
                  "menuName": "자전거",
                  "exposeStartDate": "2025-05-07 00:00:00",
                  "exposeEndDate": "2025-05-28 23:59:00",
                  "badgeType": 1,
                  "badgeExposeStartDate": "2025-05-07 00:00:00",
                  "badgeExposeEndDate": "2025-05-28 00:00:00"
                },
                {
                  "gnbSeq": 108,
                  "sortNum": 999,
                  "menuName": "닌텐도",
                  "exposeStartDate": "2025-05-12 00:00:00",
                  "exposeEndDate": "2025-06-02 23:59:00",
                  "badgeType": 1,
                  "badgeExposeStartDate": "2025-05-12 00:00:00",
                  "badgeExposeEndDate": "2025-06-02 00:00:00"
                },
                {
                  "gnbSeq": 111,
                  "sortNum": 999,
                  "menuName": "라부부",
                  "exposeStartDate": "2025-07-07 15:00:00",
                  "exposeEndDate": "2025-07-20 23:59:00",
                  "badgeType": 1,
                  "badgeExposeStartDate": "2025-07-07 15:00:00",
                  "badgeExposeEndDate": "2025-07-20 23:59:00"
                },
                {
                  "gnbSeq": 114,
                  "sortNum": 999,
                  "menuName": "A/S 보증 노트북",
                  "exposeStartDate": "2025-11-14 00:00:00",
                  "exposeEndDate": "2025-12-07 23:59:00",
                  "badgeType": 1,
                  "badgeExposeStartDate": "2025-11-14 00:00:00",
                  "badgeExposeEndDate": "2025-12-07 00:00:00"
                }
              ]
            },
            "dataUpdateCount": 1,
            "dataUpdatedAt": 1770129718709,
            "error": null,
            "errorUpdateCount": 0,
            "errorUpdatedAt": 0,
            "fetchFailureCount": 0,
            "fetchFailureReason": null,
            "fetchMeta": null,
            "isInvalidated": false,
            "status": "success",
            "fetchStatus": "idle"
          },
          "queryKey": [
            "get-gnb-list"
          ],
          "queryHash": "[\"get-gnb-list\"]"
        },
        {
          "state": {
            "data": {
              "meta": {
                "code": 0,
                "message": "SUCCESS"
              },
              "data": {
                "autoCompleteItemList": [
                  {
                    "keyword": "캠핑카"
                  },
                  {
                    "keyword": "스타렉스 캠핑카"
                  },
                  {
                    "keyword": "캠핑 트레일러"
                  },
                  {
                    "keyword": "캠핑"
                  },
                  {
                    "keyword": "캠핑트레일러"
                  },
                  {
                    "keyword": "르노마스터 캠핑카"
                  },
                  {
                    "keyword": "캠핑용품"
                  },
                  {
                    "keyword": "카운티 캠핑카"
                  },
                  {
                    "keyword": "캠핑의자"
                  },
                  {
                    "keyword": "캠핑테이블"
                  }
                ],
                "keywordCnt": 10
              }
            },
            "dataUpdateCount": 1,
            "dataUpdatedAt": 1770129718689,
            "error": null,
            "errorUpdateCount": 0,
            "errorUpdatedAt": 0,
            "fetchFailureCount": 0,
            "fetchFailureReason": null,
            "fetchMeta": null,
            "isInvalidated": false,
            "status": "success",
            "fetchStatus": "idle"
          },
          "queryKey": [
            "post-search-product-auto-complete",
            "캠핑"
          ],
          "queryHash": "[\"post-search-product-auto-complete\",\"캠핑\"]"
        },
        {
          "state": {
            "data": {
              "meta": {
                "code": 0,
                "message": "SUCCESS"
              },
              "data": {
                "transactionId": "1770129718661_-5420939447991513127",
                "emptyResult": {
                  "joongnaWebUrl": null,
                  "noticeCode": null,
                  "type": 0,
                  "buttonText": "알림 등록",
                  "buttonUrl": "",
                  "notice": "검색 결과가 없습니다.",
                  "subNotice": [
                    "검색어의 단어 수를 줄이거나",
                    "보다 일반적인 검색어로 검색해 보세요!"
                  ],
                  "image": {
                    "width": 48,
                    "height": 48,
                    "url": "https://img2.joongna.com/search/graySpeechBubble.png"
                  },
                  "loginCheck": true
                },
                "abTests": null,
                "size": 50,
                "sortOptions": [
                  {
                    "sortType": "RECOMMEND_SORT",
                    "sortName": "추천순",
                    "sortOrder": 0
                  },
                  {
                    "sortType": "RECOMMEND_SORT",
                    "sortName": "추천순",
                    "sortOrder": 0
                  },
                  {
                    "sortType": "RECENT_SORT",
                    "sortName": "최신순",
                    "sortOrder": 1
                  },
                  {
                    "sortType": "PRICE_ASC_SORT",
                    "sortName": "낮은가격순",
                    "sortOrder": 2
                  },
                  {
                    "sortType": "PRICE_DESC_SORT",
                    "sortName": "높은가격순",
                    "sortOrder": 3
                  }
                ],
                "searchFilterComponent": null,
                "filter": null,
                "totalSize": 9595,
                "searchStartDT": "2026-02-03 23:41:58",
                "items": [
                  {
                    "seq": 224846481,
                    "productPositionNo": 301,
                    "platformType": 1,
                    "price": 56800000,
                    "parcelFee": 0,
                    "url": "https://img2.joongna.com/media/original/2026/02/03/17700763366304Bj_awWs1.jpg?impolicy=thumb&size=150",
                    "title": "15년 뉴카운티5인승캠핑카(신규제작)-전액할부됨",
                    "state": 0,
                    "sortDate": "2026-02-03 08:52:18",
                    "mainLocationName": "목천읍",
                    "articleSeq": 0,
                    "articleUrl": "",
                    "videoProductYn": "N",
                    "wishCount": 0,
                    "jnPayBadgeFlag": true,
                    "pickupBadgeFlag": false,
                    "highlightedTitle": "",
                    "storeSeq": 3931190,
                    "chatCount": 0,
                    "selfAuditFlag": false,
                    "userType": 0,
                    "certifySellerFlag": false,
                    "detailImgUrl": "",
                    "locationNames": [
                      "충청남도 천안시 동남구 목천읍"
                    ],
                    "objectType": "product",
                    "wishYn": 0
                  },
                  {
                    "seq": 224784952,
                    "productPositionNo": 302,
                    "platformType": 1,
                    "price": 30000,
                    "parcelFee": 1,
                    "url": "https://img2.joongna.com/media/original/2026/02/01/1769930567338I8q_wBqvZ.jpg?impolicy=thumb&size=150",
                    "title": "산야로 캠핑용 가스버너",
                    "state": 0,
                    "sortDate": "2026-02-03 08:49:31",
                    "mainLocationName": "군포1동",
                    "articleSeq": 0,
                    "articleUrl": "",
                    "videoProductYn": "N",
                    "wishCount": 0,
                    "jnPayBadgeFlag": true,
                    "pickupBadgeFlag": false,
                    "highlightedTitle": "",
                    "storeSeq": 3351493,
                    "chatCount": 0,
                    "selfAuditFlag": false,
                    "userType": 0,
                    "certifySellerFlag": false,
                    "detailImgUrl": "",
                    "locationNames": [
                      "경기도 군포시 군포1동",
                      "경기도 군포시 산본1동",
                      "경기도 군포시 금정동"
                    ],
                    "objectType": "product",
                    "wishYn": 0
                  },
                  {
                    "seq": 224846405,
                    "productPositionNo": 303,
                    "platformType": 1,
                    "price": 18800000,
                    "parcelFee": 0,
                    "url": "https://img2.joongna.com/media/original/2026/02/03/1770076098863OLZ_wg25P.jpg?impolicy=thumb&size=150",
                    "title": "12년 e카운티25인승(숏)-할부됨,캠핑개조가능",
                    "state": 0,
                    "sortDate": "2026-02-03 08:48:20",
                    "mainLocationName": "목천읍",
                    "articleSeq": 0,
                    "articleUrl": "",
                    "videoProductYn": "N",
                    "wishCount": 0,
                    "jnPayBadgeFlag": true,
                    "pickupBadgeFlag": false,
                    "highlightedTitle": "",
                    "storeSeq": 3931190,
                    "chatCount": 1,
                    "selfAuditFlag": false,
                    "userType": 0,
                    "certifySellerFlag": false,
                    "detailImgUrl": "",
                    "locationNames": [
                      "충청남도 천안시 동남구 목천읍"
                    ],
                    "objectType": "product",
                    "wishYn": 0
                  },
                  {
                    "seq": 204884696,
                    "productPositionNo": 304,
                    "platformType": 1,
                    "price": 5000,
                    "parcelFee": 0,
                    "url": "https://img2.joongna.com/cafe-article-data/live/2025/03/22/1099875656/1742649477504_000_SnVlr_main.png?impolicy=thumb&size=150",
                    "title": "푸코 홈까페 미니 도끼칼,캠핑칼,치즈칼,빵칼 2P세트 (미개봉) - 5,000",
                    "state": 0,
                    "sortDate": "2026-02-03 08:45:18",
                    "mainLocationName": "논현1동",
                    "articleSeq": 1099875656,
                    "articleUrl": "",
                    "videoProductYn": "N",
                    "wishCount": 0,
                    "jnPayBadgeFlag": false,
                    "pickupBadgeFlag": false,
                    "highlightedTitle": "",
                    "storeSeq": 2795505,
                    "chatCount": 0,
                    "selfAuditFlag": false,
                    "userType": 0,
                    "certifySellerFlag": false,
                    "detailImgUrl": "",
                    "locationNames": [
                      "서울특별시 강남구 논현1동"
                    ],
                    "objectType": "product",
                    "wishYn": 0
                  },
                  {
                    "seq": 224846256,
                    "productPositionNo": 305,
                    "platformType": 1,
                    "price": 17800000,
                    "parcelFee": 0,
                    "url": "https://img2.joongna.com/media/original/2026/02/03/1770075696336rki_qVD4A.jpg?impolicy=thumb&size=150",
                    "title": "13.카니발2인승캠핑카(인산철600A포함풀옵션)-할부됨",
                    "state": 0,
                    "sortDate": "2026-02-03 08:41:38",
                    "mainLocationName": "목천읍",
                    "articleSeq": 0,
                    "articleUrl": "",
                    "videoProductYn": "N",
                    "wishCount": 0,
                    "jnPayBadgeFlag": true,
                    "pickupBadgeFlag": false,
                    "highlightedTitle": "",
                    "storeSeq": 3931190,
                    "chatCount": 0,
                    "selfAuditFlag": false,
                    "userType": 0,
                    "certifySellerFlag": false,
                    "detailImgUrl": "",
                    "locationNames": [
                      "충청남도 천안시 동남구 목천읍"
                    ],
                    "objectType": "product",
                    "wishYn": 0
                  },
                  {
                    "seq": 224779317,
                    "productPositionNo": 306,
                    "platformType": 1,
                    "price": 35000,
                    "parcelFee": 1,
                    "url": "https://img2.joongna.com/media/original/2026/02/01/1769922263201c3z_Nnkcc.jpg?impolicy=thumb&size=150",
                    "title": "무배새원터치텐트캠핑텐트3인ㅡ4인용양문개방방수가방36",
                    "state": 0,
                    "sortDate": "2026-02-03 08:31:45",
                    "mainLocationName": "",
                    "articleSeq": 0,
                    "articleUrl": "",
                    "videoProductYn": "N",
                    "wishCount": 0,
                    "jnPayBadgeFlag": true,
                    "pickupBadgeFlag": false,
                    "highlightedTitle": "",
                    "storeSeq": 7819887,
                    "chatCount": 0,
                    "selfAuditFlag": false,
                    "userType": 0,
                    "certifySellerFlag": false,
                    "detailImgUrl": "",
                    "locationNames": [],
                    "objectType": "product",
                    "wishYn": 0
                  },
                  {
                    "seq": 224779203,
                    "productPositionNo": 307,
                    "platformType": 1,
                    "price": 42000,
                    "parcelFee": 1,
                    "url": "https://img2.joongna.com/media/original/2026/02/01/1769922075101mwj_NxJOG.jpg?impolicy=thumb&size=150",
                    "title": "무배새원터치텐트캠핑텐트5인ㅡ6인양문개방방수가방42",
                    "state": 0,
                    "sortDate": "2026-02-03 08:31:42",
                    "mainLocationName": "",
                    "articleSeq": 0,
                    "articleUrl": "",
                    "videoProductYn": "N",
                    "wishCount": 0,
                    "jnPayBadgeFlag": true,
                    "pickupBadgeFlag": false,
                    "highlightedTitle": "",
                    "storeSeq": 7819887,
                    "chatCount": 0,
                    "selfAuditFlag": false,
                    "userType": 0,
                    "certifySellerFlag": false,
                    "detailImgUrl": "",
                    "locationNames": [],
                    "objectType": "product",
                    "wishYn": 0
                  },
                  {
                    "seq": 224620693,
                    "productPositionNo": 308,
                    "platformType": 1,
                    "price": 23000,
                    "parcelFee": 1,
                    "url": "https://img2.joongna.com/media/original/2026/01/28/17695617940494Aq_CT3iI.jpg?impolicy=thumb&size=150",
                    "title": "아이스백무배새상품캠핑초대형원단23",
                    "state": 0,
                    "sortDate": "2026-02-03 08:31:27",
                    "mainLocationName": "",
                    "articleSeq": 0,
                    "articleUrl": "",
                    "videoProductYn": "N",
                    "wishCount": 0,
                    "jnPayBadgeFlag": true,
                    "pickupBadgeFlag": false,
                    "highlightedTitle": "",
                    "storeSeq": 7819887,
                    "chatCount": 0,
                    "selfAuditFlag": false,
                    "userType": 0,
                    "certifySellerFlag": false,
                    "detailImgUrl": "",
                    "locationNames": [],
                    "objectType": "product",
                    "wishYn": 0
                  },
                  {
                    "seq": 224620646,
                    "productPositionNo": 309,
                    "platformType": 1,
                    "price": 23000,
                    "parcelFee": 1,
                    "url": "https://img2.joongna.com/media/original/2026/01/28/1769561691012xUc_60P5H.jpg?impolicy=thumb&size=150",
                    "title": "아이스박스무배새상품캠핑초대형튼튼23",
                    "state": 0,
                    "sortDate": "2026-02-03 08:31:24",
                    "mainLocationName": "",
                    "articleSeq": 0,
                    "articleUrl": "",
                    "videoProductYn": "N",
                    "wishCount": 0,
                    "jnPayBadgeFlag": true,
                    "pickupBadgeFlag": false,
                    "highlightedTitle": "",
                    "storeSeq": 7819887,
                    "chatCount": 0,
                    "selfAuditFlag": false,
                    "userType": 0,
                    "certifySellerFlag": false,
                    "detailImgUrl": "",
                    "locationNames": [],
                    "objectType": "product",
                    "wishYn": 0
                  },
                  {
                    "seq": 224620488,
                    "productPositionNo": 310,
                    "platformType": 1,
                    "price": 29000,
                    "parcelFee": 1,
                    "url": "https://img2.joongna.com/media/original/2026/01/28/1769561351721tFo_MPxTE.jpg?impolicy=thumb&size=150",
                    "title": "무배새침낭캠핑동계형4계절용따뜻방수가방30",
                    "state": 0,
                    "sortDate": "2026-02-03 08:31:21",
                    "mainLocationName": "",
                    "articleSeq": 0,
                    "articleUrl": "",
                    "videoProductYn": "N",
                    "wishCount": 0,
                    "jnPayBadgeFlag": true,
                    "pickupBadgeFlag": false,
                    "highlightedTitle": "",
                    "storeSeq": 7819887,
                    "chatCount": 0,
                    "selfAuditFlag": false,
                    "userType": 0,
                    "certifySellerFlag": false,
                    "detailImgUrl": "",
                    "locationNames": [],
                    "objectType": "product",
                    "wishYn": 0
                  },
                  {
                    "seq": 224620172,
                    "productPositionNo": 311,
                    "platformType": 1,
                    "price": 29000,
                    "parcelFee": 1,
                    "url": "https://img2.joongna.com/media/original/2026/01/28/1769560627658iqV_UaZ08.jpg?impolicy=thumb&size=150",
                    "title": "무배새침낭캠핑동계형4계절용따뜻방수가방29",
                    "state": 0,
                    "sortDate": "2026-02-03 08:31:18",
                    "mainLocationName": "",
                    "articleSeq": 0,
                    "articleUrl": "",
                    "videoProductYn": "N",
                    "wishCount": 0,
                    "jnPayBadgeFlag": true,
                    "pickupBadgeFlag": false,
                    "highlightedTitle": "",
                    "storeSeq": 7819887,
                    "chatCount": 0,
                    "selfAuditFlag": false,
                    "userType": 0,
                    "certifySellerFlag": false,
                    "detailImgUrl": "",
                    "locationNames": [],
                    "objectType": "product",
                    "wishYn": 0
                  },
                  {
                    "seq": 220447207,
                    "productPositionNo": 312,
                    "platformType": 1,
                    "price": 35000,
                    "parcelFee": 0,
                    "url": "https://img2.joongna.com/media/original/2025/10/07/17598083264424KJ_SsYUg.jpg?impolicy=thumb&size=150",
                    "title": "초경량 접이식 캠핑 의자 2개 (볼캡 포함) 팝니다.",
                    "state": 0,
                    "sortDate": "2026-02-03 08:21:54",
                    "mainLocationName": "봉림동",
                    "articleSeq": 0,
                    "articleUrl": "",
                    "videoProductYn": "N",
                    "wishCount": 0,
                    "jnPayBadgeFlag": true,
                    "pickupBadgeFlag": false,
                    "highlightedTitle": "",
                    "storeSeq": 4367668,
                    "chatCount": 0,
                    "selfAuditFlag": false,
                    "userType": 0,
                    "certifySellerFlag": false,
                    "detailImgUrl": "",
                    "locationNames": [
                      "경상남도 창원시 의창구 봉림동"
                    ],
                    "objectType": "product",
                    "wishYn": 0
                  },
                  {
                    "seq": 224845891,
                    "productPositionNo": 313,
                    "platformType": 1,
                    "price": 46800000,
                    "parcelFee": 0,
                    "url": "https://img2.joongna.com/media/original/2026/02/03/17700744383199ER_eavUt.jpg?impolicy=thumb&size=150",
                    "title": "22년형 스타리아3인승하이루프캠핑카(신규제작)-전액할부됨",
                    "state": 0,
                    "sortDate": "2026-02-03 08:20:40",
                    "mainLocationName": "목천읍",
                    "articleSeq": 0,
                    "articleUrl": "",
                    "videoProductYn": "N",
                    "wishCount": 0,
                    "jnPayBadgeFlag": true,
                    "pickupBadgeFlag": false,
                    "highlightedTitle": "",
                    "storeSeq": 3931190,
                    "chatCount": 0,
                    "selfAuditFlag": false,
                    "userType": 0,
                    "certifySellerFlag": false,
                    "detailImgUrl": "",
                    "locationNames": [
                      "충청남도 천안시 동남구 목천읍"
                    ],
                    "objectType": "product",
                    "wishYn": 0
                  },
                  {
                    "seq": 224436171,
                    "productPositionNo": 314,
                    "platformType": 1,
                    "price": 70000,
                    "parcelFee": 1,
                    "url": "https://img2.joongna.com/media/original/2026/01/23/1769135901513f5z_6tkrt.jpg?impolicy=thumb&size=150",
                    "title": "벨락 콤비9 플러스 캠핑 코펠 세트",
                    "state": 0,
                    "sortDate": "2026-02-03 08:15:39",
                    "mainLocationName": "장흥면",
                    "articleSeq": 0,
                    "articleUrl": "",
                    "videoProductYn": "N",
                    "wishCount": 0,
                    "jnPayBadgeFlag": true,
                    "pickupBadgeFlag": false,
                    "highlightedTitle": "",
                    "storeSeq": 6925208,
                    "chatCount": 1,
                    "selfAuditFlag": false,
                    "userType": 0,
                    "certifySellerFlag": false,
                    "detailImgUrl": "",
                    "locationNames": [
                      "경기도 양주시 장흥면"
                    ],
                    "objectType": "product",
                    "wishYn": 0
                  },
                  {
                    "seq": 224845760,
                    "productPositionNo": 315,
                    "platformType": 1,
                    "price": 30000,
                    "parcelFee": 0,
                    "url": "https://img2.joongna.com/media/original/2026/02/03/1770073931910ZZ5_VdIL6.jpg?impolicy=thumb&size=150",
                    "title": "와이젠 캠핑 전기난로(새상품)",
                    "state": 0,
                    "sortDate": "2026-02-03 08:12:12",
                    "mainLocationName": "호계1동",
                    "articleSeq": 0,
                    "articleUrl": "",
                    "videoProductYn": "N",
                    "wishCount": 0,
                    "jnPayBadgeFlag": true,
                    "pickupBadgeFlag": false,
                    "highlightedTitle": "",
                    "storeSeq": 12316094,
                    "chatCount": 0,
                    "selfAuditFlag": false,
                    "userType": 0,
                    "certifySellerFlag": false,
                    "detailImgUrl": "",
                    "locationNames": [
                      "경기도 안양시 동안구 호계1동"
                    ],
                    "objectType": "product",
                    "wishYn": 0
                  },
                  {
                    "seq": 223568948,
                    "productPositionNo": 316,
                    "platformType": 1,
                    "price": 65000,
                    "parcelFee": 0,
                    "url": "https://img2.joongna.com/media/original/2025/12/31/1767140110770aCJ_YiEny.jpg?impolicy=thumb&size=150",
                    "title": "보국 캠핑용 워셔블 전기요",
                    "state": 0,
                    "sortDate": "2026-02-03 08:07:20",
                    "mainLocationName": "삼각산동",
                    "articleSeq": 0,
                    "articleUrl": "",
                    "videoProductYn": "N",
                    "wishCount": 0,
                    "jnPayBadgeFlag": true,
                    "pickupBadgeFlag": false,
                    "highlightedTitle": "",
                    "storeSeq": 572956,
                    "chatCount": 0,
                    "selfAuditFlag": false,
                    "userType": 0,
                    "certifySellerFlag": false,
                    "detailImgUrl": "",
                    "locationNames": [
                      "서울특별시 강북구 삼각산동"
                    ],
                    "objectType": "product",
                    "wishYn": 0
                  },
                  {
                    "seq": 224845666,
                    "productPositionNo": 317,
                    "platformType": 1,
                    "price": 45000,
                    "parcelFee": 1,
                    "url": "https://img2.joongna.com/media/original/2026/02/03/1770073544632M1s_xRGvw.jpg?impolicy=thumb&size=150",
                    "title": "캠핑클럽 윈드브레이크 판매합니다.",
                    "state": 0,
                    "sortDate": "2026-02-03 08:05:45",
                    "mainLocationName": "신장동",
                    "articleSeq": 0,
                    "articleUrl": "",
                    "videoProductYn": "N",
                    "wishCount": 0,
                    "jnPayBadgeFlag": true,
                    "pickupBadgeFlag": false,
                    "highlightedTitle": "",
                    "storeSeq": 11080514,
                    "chatCount": 0,
                    "selfAuditFlag": false,
                    "userType": 0,
                    "certifySellerFlag": false,
                    "detailImgUrl": "",
                    "locationNames": [
                      "경기도 오산시 신장동"
                    ],
                    "objectType": "product",
                    "wishYn": 0
                  },
                  {
                    "seq": 224323389,
                    "productPositionNo": 318,
                    "platformType": 1,
                    "price": 100000,
                    "parcelFee": 0,
                    "url": "https://img2.joongna.com/media/original/2026/01/20/1768882117271eVp_zDngu.jpg?impolicy=thumb&size=150",
                    "title": "스카이라이프 아웃도어안테나 캠핑카",
                    "state": 0,
                    "sortDate": "2026-02-03 08:05:28",
                    "mainLocationName": "",
                    "articleSeq": 0,
                    "articleUrl": "",
                    "videoProductYn": "N",
                    "wishCount": 0,
                    "jnPayBadgeFlag": true,
                    "pickupBadgeFlag": false,
                    "highlightedTitle": "",
                    "storeSeq": 4054550,
                    "chatCount": 0,
                    "selfAuditFlag": false,
                    "userType": 0,
                    "certifySellerFlag": false,
                    "detailImgUrl": "",
                    "locationNames": [],
                    "objectType": "product",
                    "wishYn": 0
                  },
                  {
                    "seq": 224126118,
                    "productPositionNo": 319,
                    "platformType": 1,
                    "price": 160000,
                    "parcelFee": 0,
                    "url": "https://img2.joongna.com/media/original/2026/01/15/1768428766515Vq4_Qv5kA.jpg?impolicy=thumb&size=150",
                    "title": "골프카트, 리프트 렌탈, 캠핑카 낚시배 산업용 대용량배터리 새제품 팝니다(로케트 롱게스트)",
                    "state": 0,
                    "sortDate": "2026-02-03 07:08:01",
                    "mainLocationName": "곤지암읍",
                    "articleSeq": 0,
                    "articleUrl": "",
                    "videoProductYn": "N",
                    "wishCount": 1,
                    "jnPayBadgeFlag": true,
                    "pickupBadgeFlag": false,
                    "highlightedTitle": "",
                    "storeSeq": 1047285,
                    "chatCount": 0,
                    "selfAuditFlag": false,
                    "userType": 0,
                    "certifySellerFlag": false,
                    "detailImgUrl": "",
                    "locationNames": [
                      "경기도 광주시 곤지암읍"
                    ],
                    "objectType": "product",
                    "wishYn": 0
                  },
                  {
                    "seq": 224535673,
                    "productPositionNo": 320,
                    "platformType": 1,
                    "price": 24000,
                    "parcelFee": 0,
                    "url": "https://img2.joongna.com/media/original/2026/01/26/1769353632490zla_bE4ya.jpg?impolicy=thumb&size=150",
                    "title": "실바니안 캠핑 텐트 올드",
                    "state": 0,
                    "sortDate": "2026-02-03 07:46:44",
                    "mainLocationName": "",
                    "articleSeq": 0,
                    "articleUrl": "",
                    "videoProductYn": "N",
                    "wishCount": 0,
                    "jnPayBadgeFlag": true,
                    "pickupBadgeFlag": false,
                    "highlightedTitle": "",
                    "storeSeq": 5919797,
                    "chatCount": 0,
                    "selfAuditFlag": false,
                    "userType": 0,
                    "certifySellerFlag": false,
                    "detailImgUrl": "",
                    "locationNames": [],
                    "objectType": "product",
                    "wishYn": 0
                  },
                  {
                    "seq": 224678295,
                    "productPositionNo": 321,
                    "platformType": 1,
                    "price": 90000,
                    "parcelFee": 1,
                    "url": "https://img2.joongna.com/media/original/2026/01/29/1769676746989FTj_ukmOS.jpg?impolicy=thumb&size=150",
                    "title": "접이식 캠핑 카트 디라이프 코지 확장형 테이블 웨건 DLA-TW1000A",
                    "state": 0,
                    "sortDate": "2026-02-03 07:46:20",
                    "mainLocationName": "개포3동",
                    "articleSeq": 0,
                    "articleUrl": "",
                    "videoProductYn": "N",
                    "wishCount": 0,
                    "jnPayBadgeFlag": true,
                    "pickupBadgeFlag": false,
                    "highlightedTitle": "",
                    "storeSeq": 12131405,
                    "chatCount": 1,
                    "selfAuditFlag": false,
                    "userType": 0,
                    "certifySellerFlag": false,
                    "detailImgUrl": "",
                    "locationNames": [
                      "서울특별시 강남구 개포3동"
                    ],
                    "objectType": "product",
                    "wishYn": 0
                  },
                  {
                    "seq": 224678135,
                    "productPositionNo": 322,
                    "platformType": 1,
                    "price": 90000,
                    "parcelFee": 1,
                    "url": "https://img2.joongna.com/media/original/2026/01/29/1769676514872nsT_fFC4v.jpg?impolicy=thumb&size=150",
                    "title": "캠핑용 전기 그릴 세트 디라이프 구이스타",
                    "state": 0,
                    "sortDate": "2026-02-03 07:46:16",
                    "mainLocationName": "개포3동",
                    "articleSeq": 0,
                    "articleUrl": "",
                    "videoProductYn": "N",
                    "wishCount": 0,
                    "jnPayBadgeFlag": true,
                    "pickupBadgeFlag": false,
                    "highlightedTitle": "",
                    "storeSeq": 12131405,
                    "chatCount": 0,
                    "selfAuditFlag": false,
                    "userType": 0,
                    "certifySellerFlag": false,
                    "detailImgUrl": "",
                    "locationNames": [
                      "서울특별시 강남구 개포3동"
                    ],
                    "objectType": "product",
                    "wishYn": 0
                  },
                  {
                    "seq": 224087393,
                    "productPositionNo": 323,
                    "platformType": 1,
                    "price": 40000,
                    "parcelFee": 0,
                    "url": "https://img2.joongna.com/media/original/2026/01/14/1768345263187CzV_pK4Pt.jpg?impolicy=thumb&size=150",
                    "title": "세컨드스텝 감성캠핑 전구 20구 파티라이트 판매",
                    "state": 0,
                    "sortDate": "2026-02-03 07:39:28",
                    "mainLocationName": "비봉면",
                    "articleSeq": 0,
                    "articleUrl": "",
                    "videoProductYn": "N",
                    "wishCount": 0,
                    "jnPayBadgeFlag": true,
                    "pickupBadgeFlag": false,
                    "highlightedTitle": "",
                    "storeSeq": 10118963,
                    "chatCount": 1,
                    "selfAuditFlag": false,
                    "userType": 0,
                    "certifySellerFlag": false,
                    "detailImgUrl": "",
                    "locationNames": [
                      "경기도 화성시 비봉면"
                    ],
                    "objectType": "product",
                    "wishYn": 0
                  },
                  {
                    "seq": 224617892,
                    "productPositionNo": 324,
                    "platformType": 1,
                    "price": 40000,
                    "parcelFee": 0,
                    "url": "https://img2.joongna.com/media/original/2026/01/28/1769554282428ZbP_RLEIq.jpg?impolicy=thumb&size=150",
                    "title": "캠핑트렁크 우드 쉘프 + 가방+ S고리 정리",
                    "state": 0,
                    "sortDate": "2026-02-03 07:39:14",
                    "mainLocationName": "비봉면",
                    "articleSeq": 0,
                    "articleUrl": "",
                    "videoProductYn": "N",
                    "wishCount": 0,
                    "jnPayBadgeFlag": true,
                    "pickupBadgeFlag": false,
                    "highlightedTitle": "",
                    "storeSeq": 10118963,
                    "chatCount": 0,
                    "selfAuditFlag": false,
                    "userType": 0,
                    "certifySellerFlag": false,
                    "detailImgUrl": "",
                    "locationNames": [
                      "경기도 화성시 비봉면"
                    ],
                    "objectType": "product",
                    "wishYn": 0
                  },
                  {
                    "seq": 224106706,
                    "productPositionNo": 325,
                    "platformType": 1,
                    "price": 7000,
                    "parcelFee": 0,
                    "url": "https://img2.joongna.com/media/original/2026/01/14/176837765299796E_VSnBd.jpg?impolicy=thumb&size=150",
                    "title": "화력좋고 오래 타는 캠핑용 장작 10kg 택비포함 1만원에 팝니다",
                    "state": 0,
                    "sortDate": "2026-02-03 07:07:26",
                    "mainLocationName": "곤지암읍",
                    "articleSeq": 0,
                    "articleUrl": "",
                    "videoProductYn": "N",
                    "wishCount": 0,
                    "jnPayBadgeFlag": true,
                    "pickupBadgeFlag": false,
                    "highlightedTitle": "",
                    "storeSeq": 1047285,
                    "chatCount": 1,
                    "selfAuditFlag": false,
                    "userType": 0,
                    "certifySellerFlag": false,
                    "detailImgUrl": "",
                    "locationNames": [
                      "경기도 광주시 곤지암읍"
                    ],
                    "objectType": "product",
                    "wishYn": 0
                  },
                  {
                    "seq": 224704390,
                    "productPositionNo": 326,
                    "platformType": 1,
                    "price": 650000,
                    "parcelFee": 0,
                    "url": "https://img2.joongna.com/media/original/2026/01/30/1769745432261y5A_6dMyw.jpg?impolicy=thumb&size=150",
                    "title": "캠핑칸 마카플러스 카키 + 베스티블 + 썬가드",
                    "state": 0,
                    "sortDate": "2026-02-03 07:00:13",
                    "mainLocationName": "가창면",
                    "articleSeq": 0,
                    "articleUrl": "",
                    "videoProductYn": "N",
                    "wishCount": 0,
                    "jnPayBadgeFlag": true,
                    "pickupBadgeFlag": false,
                    "highlightedTitle": "",
                    "storeSeq": 8685349,
                    "chatCount": 0,
                    "selfAuditFlag": false,
                    "userType": 0,
                    "certifySellerFlag": false,
                    "detailImgUrl": "",
                    "locationNames": [
                      "대구광역시 달성군 가창면",
                      "대구광역시 수성구 만촌3동"
                    ],
                    "objectType": "product",
                    "wishYn": 0
                  },
                  {
                    "seq": 222125464,
                    "productPositionNo": 327,
                    "platformType": 1,
                    "price": 6500000,
                    "parcelFee": 0,
                    "url": "https://img2.joongna.com/media/original/2025/11/22/1763778028931YZ5_wvRUZ.jpg?impolicy=thumb&size=150",
                    "title": "카운티 캠핑카 급매및 대차",
                    "state": 0,
                    "sortDate": "2026-02-03 06:29:44",
                    "mainLocationName": "신중동",
                    "articleSeq": 0,
                    "articleUrl": "",
                    "videoProductYn": "N",
                    "wishCount": 16,
                    "jnPayBadgeFlag": true,
                    "pickupBadgeFlag": false,
                    "highlightedTitle": "",
                    "storeSeq": 12080118,
                    "chatCount": 9,
                    "selfAuditFlag": false,
                    "userType": 0,
                    "certifySellerFlag": false,
                    "detailImgUrl": "",
                    "locationNames": [
                      "경기도 부천시 신중동"
                    ],
                    "objectType": "product",
                    "wishYn": 0
                  },
                  {
                    "seq": 222859415,
                    "productPositionNo": 328,
                    "platformType": 1,
                    "price": 61000,
                    "parcelFee": 0,
                    "url": "https://img2.joongna.com/media/original/2025/12/11/17654577933366hV_b96kS.jpg?impolicy=thumb&size=150",
                    "title": "제로썬 에탄올난로 캠핑 가정용 알콜 불멍 팝니다",
                    "state": 0,
                    "sortDate": "2026-02-03 06:34:26",
                    "mainLocationName": "괘법동",
                    "articleSeq": 0,
                    "articleUrl": "",
                    "videoProductYn": "N",
                    "wishCount": 1,
                    "jnPayBadgeFlag": true,
                    "pickupBadgeFlag": false,
                    "highlightedTitle": "",
                    "storeSeq": 985342,
                    "chatCount": 0,
                    "selfAuditFlag": false,
                    "userType": 0,
                    "certifySellerFlag": false,
                    "detailImgUrl": "",
                    "locationNames": [
                      "부산광역시 사상구 괘법동"
                    ],
                    "objectType": "product",
                    "wishYn": 0
                  },
                  {
                    "seq": 224696371,
                    "productPositionNo": 329,
                    "platformType": 1,
                    "price": 150000,
                    "parcelFee": 0,
                    "url": "https://img2.joongna.com/media/original/2026/01/30/17697297687124b0_ZkCOb.jpg?impolicy=thumb&size=150",
                    "title": "카투어 K35 캠핑 냉장고 35L + 지니 전용 가방",
                    "state": 0,
                    "sortDate": "2026-02-03 06:59:58",
                    "mainLocationName": "가창면",
                    "articleSeq": 0,
                    "articleUrl": "",
                    "videoProductYn": "N",
                    "wishCount": 0,
                    "jnPayBadgeFlag": true,
                    "pickupBadgeFlag": false,
                    "highlightedTitle": "",
                    "storeSeq": 8685349,
                    "chatCount": 0,
                    "selfAuditFlag": false,
                    "userType": 0,
                    "certifySellerFlag": false,
                    "detailImgUrl": "",
                    "locationNames": [
                      "대구광역시 달성군 가창면",
                      "대구광역시 수성구 만촌3동"
                    ],
                    "objectType": "product",
                    "wishYn": 0
                  },
                  {
                    "seq": 224731451,
                    "productPositionNo": 330,
                    "platformType": 1,
                    "price": 27000,
                    "parcelFee": 0,
                    "url": "https://img2.joongna.com/media/original/2026/01/31/1769809357901kOe_hyTXU.jpg?impolicy=thumb&size=150",
                    "title": "라코스테 스타빅스 캠핑의자 그린 아이보리 폴딩체어 프리퀸시 새상품 미개봉",
                    "state": 0,
                    "sortDate": "2026-02-03 06:54:44",
                    "mainLocationName": "",
                    "articleSeq": 0,
                    "articleUrl": "",
                    "videoProductYn": "N",
                    "wishCount": 0,
                    "jnPayBadgeFlag": true,
                    "pickupBadgeFlag": false,
                    "highlightedTitle": "",
                    "storeSeq": 11938254,
                    "chatCount": 0,
                    "selfAuditFlag": false,
                    "userType": 0,
                    "certifySellerFlag": false,
                    "detailImgUrl": "",
                    "locationNames": [],
                    "objectType": "product",
                    "wishYn": 0
                  },
                  {
                    "seq": 221349419,
                    "productPositionNo": 331,
                    "platformType": 1,
                    "price": 15000,
                    "parcelFee": 0,
                    "url": "https://img2.joongna.com/media/original/2026/02/01/176992924827967o_aXIFe.jpg?impolicy=thumb&size=150",
                    "title": "[미개봉 제품] EQL 캠핑용 접이식 의자 폴딩 체어",
                    "state": 0,
                    "sortDate": "2026-02-03 06:50:21",
                    "mainLocationName": "송파1동",
                    "articleSeq": 0,
                    "articleUrl": "",
                    "videoProductYn": "N",
                    "wishCount": 0,
                    "jnPayBadgeFlag": true,
                    "pickupBadgeFlag": false,
                    "highlightedTitle": "",
                    "storeSeq": 9915518,
                    "chatCount": 0,
                    "selfAuditFlag": false,
                    "userType": 0,
                    "certifySellerFlag": false,
                    "detailImgUrl": "",
                    "locationNames": [
                      "서울특별시 송파구 송파1동"
                    ],
                    "objectType": "product",
                    "wishYn": 0
                  },
                  {
                    "seq": 224783720,
                    "productPositionNo": 332,
                    "platformType": 1,
                    "price": 25000,
                    "parcelFee": 0,
                    "url": "https://img2.joongna.com/media/original/2026/02/01/1769928901329VZa_h94BN.jpg?impolicy=thumb&size=150",
                    "title": "[미개봉 제품] 스타벅스 x 헬리녹스 캠핑 사이드 테이블 아이보리",
                    "state": 0,
                    "sortDate": "2026-02-03 06:50:05",
                    "mainLocationName": "송파1동",
                    "articleSeq": 0,
                    "articleUrl": "",
                    "videoProductYn": "N",
                    "wishCount": 0,
                    "jnPayBadgeFlag": true,
                    "pickupBadgeFlag": false,
                    "highlightedTitle": "",
                    "storeSeq": 9915518,
                    "chatCount": 0,
                    "selfAuditFlag": false,
                    "userType": 0,
                    "certifySellerFlag": false,
                    "detailImgUrl": "",
                    "locationNames": [
                      "서울특별시 송파구 송파1동"
                    ],
                    "objectType": "product",
                    "wishYn": 0
                  },
                  {
                    "seq": 224783656,
                    "productPositionNo": 333,
                    "platformType": 1,
                    "price": 30000,
                    "parcelFee": 0,
                    "url": "https://img2.joongna.com/media/original/2026/02/01/1769928801673zo2_bQbRs.jpg?impolicy=thumb&size=150",
                    "title": "[미개봉 제품] 레벤트 캠핑 테이블 램프 TL160 LED 랜턴 조명",
                    "state": 0,
                    "sortDate": "2026-02-03 06:49:57",
                    "mainLocationName": "송파1동",
                    "articleSeq": 0,
                    "articleUrl": "",
                    "videoProductYn": "N",
                    "wishCount": 0,
                    "jnPayBadgeFlag": true,
                    "pickupBadgeFlag": false,
                    "highlightedTitle": "",
                    "storeSeq": 9915518,
                    "chatCount": 0,
                    "selfAuditFlag": false,
                    "userType": 0,
                    "certifySellerFlag": false,
                    "detailImgUrl": "",
                    "locationNames": [
                      "서울특별시 송파구 송파1동"
                    ],
                    "objectType": "product",
                    "wishYn": 0
                  },
                  {
                    "seq": 224771799,
                    "productPositionNo": 334,
                    "platformType": 1,
                    "price": 30000,
                    "parcelFee": 0,
                    "url": "https://img2.joongna.com/media/original/2026/02/01/1769909323831K7T_uy6hX.jpg?impolicy=thumb&size=150",
                    "title": "캠핑led등",
                    "state": 0,
                    "sortDate": "2026-02-03 06:20:07",
                    "mainLocationName": "원성1동",
                    "articleSeq": 0,
                    "articleUrl": "",
                    "videoProductYn": "N",
                    "wishCount": 0,
                    "jnPayBadgeFlag": true,
                    "pickupBadgeFlag": false,
                    "highlightedTitle": "",
                    "storeSeq": 7246828,
                    "chatCount": 0,
                    "selfAuditFlag": false,
                    "userType": 0,
                    "certifySellerFlag": false,
                    "detailImgUrl": "",
                    "locationNames": [
                      "충청남도 천안시 동남구 원성1동"
                    ],
                    "objectType": "product",
                    "wishYn": 0
                  },
                  {
                    "seq": 224771499,
                    "productPositionNo": 335,
                    "platformType": 1,
                    "price": 30000,
                    "parcelFee": 0,
                    "url": "https://img2.joongna.com/media/original/2026/02/01/1769908781358e4o_Q3w2c.jpg?impolicy=thumb&size=150",
                    "title": "캠핑카 카라반 청수통필터",
                    "state": 0,
                    "sortDate": "2026-02-03 06:19:53",
                    "mainLocationName": "원성1동",
                    "articleSeq": 0,
                    "articleUrl": "",
                    "videoProductYn": "N",
                    "wishCount": 0,
                    "jnPayBadgeFlag": true,
                    "pickupBadgeFlag": false,
                    "highlightedTitle": "",
                    "storeSeq": 7246828,
                    "chatCount": 0,
                    "selfAuditFlag": false,
                    "userType": 0,
                    "certifySellerFlag": false,
                    "detailImgUrl": "",
                    "locationNames": [
                      "충청남도 천안시 동남구 원성1동"
                    ],
                    "objectType": "product",
                    "wishYn": 0
                  },
                  {
                    "seq": 224484783,
                    "productPositionNo": 336,
                    "platformType": 1,
                    "price": 150000,
                    "parcelFee": 0,
                    "url": "https://img2.joongna.com/media/original/2026/01/24/17692431620507xj_EP0MQ.jpg?impolicy=thumb&size=150",
                    "title": "캠핑용 냉장고",
                    "state": 0,
                    "sortDate": "2026-02-03 06:18:33",
                    "mainLocationName": "원성1동",
                    "articleSeq": 0,
                    "articleUrl": "",
                    "videoProductYn": "N",
                    "wishCount": 0,
                    "jnPayBadgeFlag": true,
                    "pickupBadgeFlag": false,
                    "highlightedTitle": "",
                    "storeSeq": 7246828,
                    "chatCount": 0,
                    "selfAuditFlag": false,
                    "userType": 0,
                    "certifySellerFlag": false,
                    "detailImgUrl": "",
                    "locationNames": [
                      "충청남도 천안시 동남구 원성1동"
                    ],
                    "objectType": "product",
                    "wishYn": 0
                  },
                  {
                    "seq": 224540068,
                    "productPositionNo": 337,
                    "platformType": 1,
                    "price": 50000,
                    "parcelFee": 0,
                    "url": "https://img2.joongna.com/media/original/2026/01/26/1769384255317K9B_8jXMM.jpg?impolicy=thumb&size=150",
                    "title": "캠핑아궁이 화로대+팬",
                    "state": 0,
                    "sortDate": "2026-02-03 06:17:48",
                    "mainLocationName": "원성1동",
                    "articleSeq": 0,
                    "articleUrl": "",
                    "videoProductYn": "N",
                    "wishCount": 0,
                    "jnPayBadgeFlag": true,
                    "pickupBadgeFlag": false,
                    "highlightedTitle": "",
                    "storeSeq": 7246828,
                    "chatCount": 0,
                    "selfAuditFlag": false,
                    "userType": 0,
                    "certifySellerFlag": false,
                    "detailImgUrl": "",
                    "locationNames": [
                      "충청남도 천안시 동남구 원성1동"
                    ],
                    "objectType": "product",
                    "wishYn": 0
                  },
                  {
                    "seq": 224503938,
                    "productPositionNo": 338,
                    "platformType": 1,
                    "price": 55000,
                    "parcelFee": 0,
                    "url": "https://img2.joongna.com/media/original/2026/01/25/1769300716563exn_xvOWP.jpg?impolicy=thumb&size=150",
                    "title": "캠핑캐비넷",
                    "state": 0,
                    "sortDate": "2026-02-03 06:17:42",
                    "mainLocationName": "원성1동",
                    "articleSeq": 0,
                    "articleUrl": "",
                    "videoProductYn": "N",
                    "wishCount": 0,
                    "jnPayBadgeFlag": true,
                    "pickupBadgeFlag": false,
                    "highlightedTitle": "",
                    "storeSeq": 7246828,
                    "chatCount": 0,
                    "selfAuditFlag": false,
                    "userType": 0,
                    "certifySellerFlag": false,
                    "detailImgUrl": "",
                    "locationNames": [
                      "충청남도 천안시 동남구 원성1동"
                    ],
                    "objectType": "product",
                    "wishYn": 0
                  },
                  {
                    "seq": 224503959,
                    "productPositionNo": 339,
                    "platformType": 1,
                    "price": 50000,
                    "parcelFee": 0,
                    "url": "https://img2.joongna.com/media/original/2026/01/25/1769300786234R9Y_Nfek6.jpg?impolicy=thumb&size=150",
                    "title": "캠핑아궁이+팬",
                    "state": 0,
                    "sortDate": "2026-02-03 06:17:35",
                    "mainLocationName": "원성1동",
                    "articleSeq": 0,
                    "articleUrl": "",
                    "videoProductYn": "N",
                    "wishCount": 0,
                    "jnPayBadgeFlag": true,
                    "pickupBadgeFlag": false,
                    "highlightedTitle": "",
                    "storeSeq": 7246828,
                    "chatCount": 0,
                    "selfAuditFlag": false,
                    "userType": 0,
                    "certifySellerFlag": false,
                    "detailImgUrl": "",
                    "locationNames": [
                      "충청남도 천안시 동남구 원성1동"
                    ],
                    "objectType": "product",
                    "wishYn": 0
                  },
                  {
                    "seq": 224607147,
                    "productPositionNo": 340,
                    "platformType": 1,
                    "price": 20000,
                    "parcelFee": 0,
                    "url": "https://img2.joongna.com/media/original/2026/01/27/17695155256981Nb_o7yVp.jpg?impolicy=thumb&size=150",
                    "title": "캠핑용품6개.새상품",
                    "state": 0,
                    "sortDate": "2026-02-03 06:17:07",
                    "mainLocationName": "원성1동",
                    "articleSeq": 0,
                    "articleUrl": "",
                    "videoProductYn": "N",
                    "wishCount": 0,
                    "jnPayBadgeFlag": true,
                    "pickupBadgeFlag": false,
                    "highlightedTitle": "",
                    "storeSeq": 7246828,
                    "chatCount": 0,
                    "selfAuditFlag": false,
                    "userType": 0,
                    "certifySellerFlag": false,
                    "detailImgUrl": "",
                    "locationNames": [
                      "충청남도 천안시 동남구 원성1동"
                    ],
                    "objectType": "product",
                    "wishYn": 0
                  },
                  {
                    "seq": 224844572,
                    "productPositionNo": 341,
                    "platformType": 1,
                    "price": 7000,
                    "parcelFee": 0,
                    "url": "https://img2.joongna.com/media/original/2026/02/03/17700657493161NR_Fh4ob.jpg?impolicy=thumb&size=150",
                    "title": "앵두전구 10미터(감성인테리어,캠핑)15000원",
                    "state": 0,
                    "sortDate": "2026-02-03 05:55:49",
                    "mainLocationName": "형곡1동",
                    "articleSeq": 0,
                    "articleUrl": "",
                    "videoProductYn": "N",
                    "wishCount": 0,
                    "jnPayBadgeFlag": true,
                    "pickupBadgeFlag": false,
                    "highlightedTitle": "",
                    "storeSeq": 5895658,
                    "chatCount": 0,
                    "selfAuditFlag": false,
                    "userType": 0,
                    "certifySellerFlag": false,
                    "detailImgUrl": "",
                    "locationNames": [
                      "경상북도 구미시 형곡1동"
                    ],
                    "objectType": "product",
                    "wishYn": 0
                  },
                  {
                    "seq": 224834715,
                    "productPositionNo": 342,
                    "platformType": 1,
                    "price": 40000,
                    "parcelFee": 0,
                    "url": "https://img2.joongna.com/media/original/2026/02/02/1770033770424C6n_LFhvS.jpg?impolicy=thumb&size=150",
                    "title": "포켓베드 워셔블 차박 캠핑용 DC 12V/AC겸용 캠핑프로 고급형 온열매트",
                    "state": 0,
                    "sortDate": "2026-02-03 05:40:23",
                    "mainLocationName": "장성읍",
                    "articleSeq": 0,
                    "articleUrl": "",
                    "videoProductYn": "N",
                    "wishCount": 0,
                    "jnPayBadgeFlag": true,
                    "pickupBadgeFlag": false,
                    "highlightedTitle": "",
                    "storeSeq": 10088587,
                    "chatCount": 0,
                    "selfAuditFlag": false,
                    "userType": 0,
                    "certifySellerFlag": false,
                    "detailImgUrl": "",
                    "locationNames": [
                      "전라남도 장성군 장성읍"
                    ],
                    "objectType": "product",
                    "wishYn": 0
                  },
                  {
                    "seq": 224649094,
                    "productPositionNo": 343,
                    "platformType": 1,
                    "price": 60000,
                    "parcelFee": 0,
                    "url": "https://img2.joongna.com/media/original/2026/01/28/1769605089755Atp_bqnhD.jpg?impolicy=thumb&size=150",
                    "title": "포켓베드 워셔블 차박 캠핑용 DC 12V/AC겸용 캠핑프로 고급형 온열매트",
                    "state": 0,
                    "sortDate": "2026-02-03 05:39:50",
                    "mainLocationName": "장성읍",
                    "articleSeq": 0,
                    "articleUrl": "",
                    "videoProductYn": "N",
                    "wishCount": 0,
                    "jnPayBadgeFlag": true,
                    "pickupBadgeFlag": false,
                    "highlightedTitle": "",
                    "storeSeq": 10088587,
                    "chatCount": 0,
                    "selfAuditFlag": false,
                    "userType": 0,
                    "certifySellerFlag": false,
                    "detailImgUrl": "",
                    "locationNames": [
                      "전라남도 장성군 장성읍"
                    ],
                    "objectType": "product",
                    "wishYn": 0
                  },
                  {
                    "seq": 220486553,
                    "productPositionNo": 344,
                    "platformType": 1,
                    "price": 110000,
                    "parcelFee": 0,
                    "url": "https://img2.joongna.com/media/original/2025/10/08/1759916174653tx5_iRkge.jpg?impolicy=thumb&size=150",
                    "title": "파세코 PGH-B1400, 캠핑문 연결 분배기 Z30+",
                    "state": 0,
                    "sortDate": "2026-02-03 05:38:39",
                    "mainLocationName": "비전2동",
                    "articleSeq": 0,
                    "articleUrl": "",
                    "videoProductYn": "N",
                    "wishCount": 0,
                    "jnPayBadgeFlag": true,
                    "pickupBadgeFlag": false,
                    "highlightedTitle": "",
                    "storeSeq": 10389615,
                    "chatCount": 0,
                    "selfAuditFlag": false,
                    "userType": 0,
                    "certifySellerFlag": false,
                    "detailImgUrl": "",
                    "locationNames": [
                      "경기도 평택시 비전2동"
                    ],
                    "objectType": "product",
                    "wishYn": 0
                  },
                  {
                    "seq": 224202917,
                    "productPositionNo": 345,
                    "platformType": 1,
                    "price": 3250000,
                    "parcelFee": 0,
                    "url": "https://img2.joongna.com/media/original/2026/01/17/1768607677757loD_9uk36.jpg?impolicy=thumb&size=150",
                    "title": "코쿤 CT1 캠핑 카고 트레일러",
                    "state": 0,
                    "sortDate": "2026-02-03 04:12:56",
                    "mainLocationName": "강화읍",
                    "articleSeq": 0,
                    "articleUrl": "",
                    "videoProductYn": "N",
                    "wishCount": 3,
                    "jnPayBadgeFlag": true,
                    "pickupBadgeFlag": false,
                    "highlightedTitle": "",
                    "storeSeq": 12261436,
                    "chatCount": 0,
                    "selfAuditFlag": false,
                    "userType": 0,
                    "certifySellerFlag": false,
                    "detailImgUrl": "",
                    "locationNames": [
                      "인천광역시 강화군 강화읍"
                    ],
                    "objectType": "product",
                    "wishYn": 0
                  },
                  {
                    "seq": 223308833,
                    "productPositionNo": 346,
                    "platformType": 1,
                    "price": 68000,
                    "parcelFee": 0,
                    "url": "https://img2.joongna.com/media/original/2025/12/24/17665040675305Ll_HeTe0.jpg?impolicy=thumb&size=150",
                    "title": "캠핑 연기없이 숮불화로 로스타 테이블 타공 연통 숯불구 타공 후드 #새상품#",
                    "state": 0,
                    "sortDate": "2026-02-03 03:02:20",
                    "mainLocationName": "진영읍",
                    "articleSeq": 0,
                    "articleUrl": "",
                    "videoProductYn": "Y",
                    "wishCount": 0,
                    "jnPayBadgeFlag": true,
                    "pickupBadgeFlag": false,
                    "highlightedTitle": "",
                    "storeSeq": 1571579,
                    "chatCount": 0,
                    "selfAuditFlag": false,
                    "userType": 0,
                    "certifySellerFlag": false,
                    "detailImgUrl": "",
                    "locationNames": [
                      "경상남도 김해시 진영읍"
                    ],
                    "objectType": "product",
                    "wishYn": 0
                  },
                  {
                    "seq": 223451485,
                    "productPositionNo": 347,
                    "platformType": 1,
                    "price": 68000,
                    "parcelFee": 0,
                    "url": "https://img2.joongna.com/media/original/2025/12/28/1766865991079jII_99ESw.jpg?impolicy=thumb&size=150",
                    "title": "캠핑 연기없이 숮불화로 로스타 테이블 타공 연통 숯불구 후드 #새상품#",
                    "state": 0,
                    "sortDate": "2026-02-03 03:01:28",
                    "mainLocationName": "진영읍",
                    "articleSeq": 0,
                    "articleUrl": "",
                    "videoProductYn": "N",
                    "wishCount": 0,
                    "jnPayBadgeFlag": true,
                    "pickupBadgeFlag": false,
                    "highlightedTitle": "",
                    "storeSeq": 1571579,
                    "chatCount": 0,
                    "selfAuditFlag": false,
                    "userType": 0,
                    "certifySellerFlag": false,
                    "detailImgUrl": "",
                    "locationNames": [
                      "경상남도 김해시 진영읍"
                    ],
                    "objectType": "product",
                    "wishYn": 0
                  },
                  {
                    "seq": 224843770,
                    "productPositionNo": 348,
                    "platformType": 1,
                    "price": 20000,
                    "parcelFee": 0,
                    "url": "https://img2.joongna.com/media/original/2026/02/03/1770055283291lb3_eNkSO.jpg?impolicy=thumb&size=150",
                    "title": "대동 캠핑용 차량용 레트로 소화기(미사용 새제품)",
                    "state": 0,
                    "sortDate": "2026-02-03 03:01:24",
                    "mainLocationName": "백석동",
                    "articleSeq": 0,
                    "articleUrl": "",
                    "videoProductYn": "N",
                    "wishCount": 0,
                    "jnPayBadgeFlag": true,
                    "pickupBadgeFlag": false,
                    "highlightedTitle": "",
                    "storeSeq": 12221709,
                    "chatCount": 0,
                    "selfAuditFlag": false,
                    "userType": 0,
                    "certifySellerFlag": false,
                    "detailImgUrl": "",
                    "locationNames": [
                      "충청남도 천안시 서북구 백석동",
                      "충청남도 천안시 동남구 신안동"
                    ],
                    "objectType": "product",
                    "wishYn": 0
                  },
                  {
                    "seq": 221261822,
                    "productPositionNo": 349,
                    "platformType": 1,
                    "price": 10000,
                    "parcelFee": 0,
                    "url": "https://img2.joongna.com/media/original/2025/10/29/1761745959222V2Z_XIfuG.jpg?impolicy=thumb&size=150",
                    "title": "새상품 국내생산 아토누리 기모바지 등원룩 캠핑룩 140",
                    "state": 0,
                    "sortDate": "2026-02-03 00:18:37",
                    "mainLocationName": "",
                    "articleSeq": 0,
                    "articleUrl": "",
                    "videoProductYn": "N",
                    "wishCount": 2,
                    "jnPayBadgeFlag": true,
                    "pickupBadgeFlag": false,
                    "highlightedTitle": "",
                    "storeSeq": 900356,
                    "chatCount": 0,
                    "selfAuditFlag": false,
                    "userType": 0,
                    "certifySellerFlag": false,
                    "detailImgUrl": "",
                    "locationNames": [],
                    "objectType": "product",
                    "wishYn": 0
                  },
                  {
                    "seq": 222550814,
                    "productPositionNo": 350,
                    "platformType": 1,
                    "price": 45000,
                    "parcelFee": 0,
                    "url": "https://img2.joongna.com/media/original/2025/12/03/17647493853922nM_dxrxA.jpg?impolicy=thumb&size=150",
                    "title": "캠핑 화로 테이블",
                    "state": 0,
                    "sortDate": "2026-02-03 00:49:29",
                    "mainLocationName": "성내제3동",
                    "articleSeq": 0,
                    "articleUrl": "",
                    "videoProductYn": "N",
                    "wishCount": 0,
                    "jnPayBadgeFlag": true,
                    "pickupBadgeFlag": false,
                    "highlightedTitle": "",
                    "storeSeq": 7590756,
                    "chatCount": 0,
                    "selfAuditFlag": false,
                    "userType": 0,
                    "certifySellerFlag": false,
                    "detailImgUrl": "",
                    "locationNames": [
                      "서울특별시 강동구 성내제3동"
                    ],
                    "objectType": "product",
                    "wishYn": 0
                  }
                ],
                "changedProductFilterType": false,
                "changedKeyword": {
                  "isChangedKeyword": false,
                  "originKeyword": "캠핑",
                  "changedKeyword": "캠핑"
                },
                "selfAuditRecommendItems": [],
                "standardPriceShow": 0,
                "resultType": 0
              }
            },
            "dataUpdateCount": 1,
            "dataUpdatedAt": 1770129718665,
            "error": null,
            "errorUpdateCount": 0,
            "errorUpdatedAt": 0,
            "fetchFailureCount": 0,
            "fetchFailureReason": null,
            "fetchMeta": null,
            "isInvalidated": false,
            "status": "success",
            "fetchStatus": "idle"
          },
          "queryKey": [
            "get-search-products",
            {
              "categoryFilter": [
                {
                  "categoryDepth": 0,
                  "categorySeq": 0
                }
              ],
              "firstQuantity": 50,
              "jnPayYn": "ALL",
              "keywordSource": "INPUT_KEYWORD",
              "osType": 2,
              "page": 6,
              "parcelFeeYn": "ALL",
              "priceFilter": {
                "maxPrice": 100000000,
                "minPrice": 0
              },
              "quantity": 50,
              "registPeriod": "ALL",
              "saleYn": "SALE_N",
              "sort": "RECOMMEND_SORT",
              "filterTypeCheckoutByUser": false,
              "adjustSearchKeyword": true,
              "searchWord": "캠핑"
            }
          ],
          "queryHash": "[\"get-search-products\",{\"adjustSearchKeyword\":true,\"categoryFilter\":[{\"categoryDepth\":0,\"categorySeq\":0}],\"filterTypeCheckoutByUser\":false,\"firstQuantity\":50,\"jnPayYn\":\"ALL\",\"keywordSource\":\"INPUT_KEYWORD\",\"osType\":2,\"page\":6,\"parcelFeeYn\":\"ALL\",\"priceFilter\":{\"maxPrice\":100000000,\"minPrice\":0},\"quantity\":50,\"registPeriod\":\"ALL\",\"saleYn\":\"SALE_N\",\"searchWord\":\"캠핑\",\"sort\":\"RECOMMEND_SORT\"}]"
        },
        {
          "state": {
            "data": {
              "meta": {
                "code": 0,
                "message": "SUCCESS"
              },
              "data": {
                "searchKeyword": [
                  "캠핑"
                ],
                "relatedKeywordList": [
                  {
                    "relatedKeyword": "테이블",
                    "toSearch": "캠핑 테이블",
                    "type": "right"
                  },
                  {
                    "relatedKeyword": "의자",
                    "toSearch": "캠핑 의자",
                    "type": "right"
                  },
                  {
                    "relatedKeyword": "식탁",
                    "toSearch": "식탁",
                    "type": "jaccard"
                  }
                ]
              }
            },
            "dataUpdateCount": 1,
            "dataUpdatedAt": 1770129718578,
            "error": null,
            "errorUpdateCount": 0,
            "errorUpdatedAt": 0,
            "fetchFailureCount": 0,
            "fetchFailureReason": null,
            "fetchMeta": null,
            "isInvalidated": false,
            "status": "success",
            "fetchStatus": "idle"
          },
          "queryKey": [
            "get-search-related-keyword",
            "캠핑"
          ],
          "queryHash": "[\"get-search-related-keyword\",\"캠핑\"]"
        },
        {
          "state": {
            "data": {
              "storeSeq": null
            },
            "dataUpdateCount": 1,
            "dataUpdatedAt": 1770129718547,
            "error": null,
            "errorUpdateCount": 0,
            "errorUpdatedAt": 0,
            "fetchFailureCount": 0,
            "fetchFailureReason": null,
            "fetchMeta": null,
            "isInvalidated": false,
            "status": "success",
            "fetchStatus": "idle"
          },
          "queryKey": [
            "my-store-seq"
          ],
          "queryHash": "[\"my-store-seq\"]"
        }
      ]
    },
    "session": {
      "status": "unauthenticated"
    },
    "_sentryTraceData": "5d28fe23972140ce81b53dde126a73fe-74a7ca6762acb8a3",
    "_sentryBaggage": "sentry-environment=live,sentry-release=h0ZBTp8QguUS6pcWFFXzx,sentry-public_key=a8d4ca8a3deee185a932c6711cbfc02c,sentry-trace_id=5d28fe23972140ce81b53dde126a73fe"
  },
  "__N_SSP": true
}